AUTHORS
LICENSE
README.md
setup.cfg
setup.py
act/api/__init__.py
act/api/base.py
act/api/fact.py
act/api/helpers.py
act/api/obj.py
act/api/re.py
act/api/schema.py
act/api/utils.py
act/api/libs/__init__.py
act/api/libs/cli.py
act_api.egg-info/PKG-INFO
act_api.egg-info/SOURCES.txt
act_api.egg-info/dependency_links.txt
act_api.egg-info/namespace_packages.txt
act_api.egg-info/requires.txt
act_api.egg-info/top_level.txt
test/test_base.py
test/test_fact.py
test/test_helpers.py
test/test_object.py
test/test_origin.py
test/test_schema.py