Metadata-Version: 2.1
Name: act-api
Version: 2.1.0
Summary: Python library to connect to the ACT rest API
Home-page: https://github.com/mnemonic-no
Author: mnemonic AS
Author-email: opensource@mnemonic.no
License: MIT
Keywords: ACT,mnemonic
Classifier: Development Status :: 4 - Beta
Classifier: Topic :: Utilities
Classifier: License :: OSI Approved :: ISC License (ISCL)
Requires-Python: >=2.7, !=3.0.*, !=3.1.*, !=3.2.*, !=3.3.*, <4
License-File: LICENSE
License-File: AUTHORS
